odoo/addons/account_maturity_date_default/README.rst
odoo/addons/account_maturity_date_default/__init__.py
odoo/addons/account_maturity_date_default/__manifest__.py
odoo/addons/account_maturity_date_default/i18n/account_maturity_date_default.pot
odoo/addons/account_maturity_date_default/models/__init__.py
odoo/addons/account_maturity_date_default/models/account_move.py
odoo/addons/account_maturity_date_default/models/account_move_line.py
odoo/addons/account_maturity_date_default/readme/CONTRIBUTORS.rst
odoo/addons/account_maturity_date_default/readme/DESCRIPTION.rst
odoo/addons/account_maturity_date_default/static/description/icon.png
odoo/addons/account_maturity_date_default/static/description/index.html
odoo/addons/account_maturity_date_default/tests/__init__.py
odoo/addons/account_maturity_date_default/tests/test_account_move.py
odoo13_addon_account_maturity_date_default-13.0.2.0.0.dist-info/METADATA
odoo13_addon_account_maturity_date_default-13.0.2.0.0.dist-info/WHEEL
odoo13_addon_account_maturity_date_default-13.0.2.0.0.dist-info/top_level.txt
odoo13_addon_account_maturity_date_default-13.0.2.0.0.dist-info/RECORD
