Metadata-Version: 2.1
Name: odoo13-addon-account-maturity-date-default
Version: 13.0.2.0.0
Summary: Account Maturity Date Default
Home-page: https://github.com/OCA/account-financial-tools
Author: Tecnativa, Odoo Community Association (OCA)
Author-email: support@odoo-community.org
License: AGPL-3
Platform: UNKNOWN
Classifier: Programming Language :: Python
Classifier: Framework :: Odoo
Classifier: License :: OSI Approved :: GNU Affero General Public License v3
Requires-Python: >=3.5
Requires-Dist: odoo (<13.1dev,>=13.0a)
